data_science_bowl_2019/__init__.py
data_science_bowl_2019/_nbdev.py
data_science_bowl_2019/lda.py
data_science_bowl_2019/wide_and_deep.py
data_science_bowl_2019-1.0.1.dist-info/LICENSE.md
data_science_bowl_2019-1.0.1.dist-info/METADATA
data_science_bowl_2019-1.0.1.dist-info/WHEEL
data_science_bowl_2019-1.0.1.dist-info/entry_points.txt
data_science_bowl_2019-1.0.1.dist-info/top_level.txt
data_science_bowl_2019-1.0.1.dist-info/RECORD
