Metadata-Version: 2.1
Name: data-science-bowl-2019
Version: 1.0.1
Summary: The notebooks for the competition Data Science Bowl 2019.
Home-page: https://github.com/JiaxiangBU/data-science-bowl-2019EX
Author: Jiaxiang Li and Jiatao Li
Author-email: alex.lijiaxiang@foxmail.com
License: Apache Software License 2.0
Keywords: wide_and_deep LDA
Platform: UNKNOWN
Classifier: Development Status :: 3 - Alpha
Classifier: Intended Audience :: Developers
Classifier: License :: OSI Approved :: Apache Software License
Classifier: Natural Language :: English
Classifier: Programming Language :: Python :: 3.6
Classifier: Programming Language :: Python :: 3.7
Classifier: Programming Language :: Python :: 3.8
Requires-Python: >=3.6
